degirum_tools/__init__.py
degirum_tools/_version.py
degirum_tools/inference_support.py
degirum_tools/logo.ico
degirum_tools/remote_assets.py
degirum_tools/analyzers/__init__.py
degirum_tools/analyzers/clip_saver.py
degirum_tools/analyzers/event_detector.py
degirum_tools/analyzers/line_count.py
degirum_tools/analyzers/notifier.py
degirum_tools/analyzers/object_selector.py
degirum_tools/analyzers/object_tracker.py
degirum_tools/analyzers/result_analyzer_base.py
degirum_tools/analyzers/zone_count.py
degirum_tools/compound_models/__init__.py
degirum_tools/compound_models/compound_models.py
degirum_tools/compound_models/tile_compound_models.py
degirum_tools/evaluators/__init__.py
degirum_tools/evaluators/classification_eval.py
degirum_tools/evaluators/detection_eval.py
degirum_tools/evaluators/eval_support.py
degirum_tools/evaluators/regression_eval.py
degirum_tools/streams/__init__.py
degirum_tools/streams/base.py
degirum_tools/streams/gizmos.py
degirum_tools/tools/__init__.py
degirum_tools/tools/audio_support.py
degirum_tools/tools/crop_extent.py
degirum_tools/tools/environment.py
degirum_tools/tools/expr_substitute.py
degirum_tools/tools/figure_annotator.py
degirum_tools/tools/gst_support.py
degirum_tools/tools/image_tools.py
degirum_tools/tools/math_support.py
degirum_tools/tools/model_registry.py
degirum_tools/tools/object_storage_support.py
degirum_tools/tools/ui_support.py
degirum_tools/tools/video_support.py
degirum_tools-0.25.1.dist-info/licenses/LICENSE
degirum_tools-0.25.1.dist-info/METADATA
degirum_tools-0.25.1.dist-info/WHEEL
degirum_tools-0.25.1.dist-info/entry_points.txt
degirum_tools-0.25.1.dist-info/top_level.txt
degirum_tools-0.25.1.dist-info/RECORD
